{
	"database": "/opt/xchem-fragalysis-2/maxwin/CHIKV_HIPPO/hippo_prod/CHIKV_prod9b.sqlite",
	"timestamp": "2024-10-12 11:13:19.135126",
	"price": {
		"amount": 10000.0,
		"currency": "EUR"
	},
	"reactant_supplier": [
		"Stock",
		"Enamine"
	],
	"reactants": {
		"compound_id": [
			85,
			4554,
			4466,
			4467,
			4440,
			4530,
			4445,
			4480,
			4545,
			4546,
			4557,
			4558,
			4534,
			4535,
			4505,
			4507,
			84,
			4472,
			4449,
			4450,
			4439,
			4451,
			4444,
			4476,
			4477,
			4452,
			4483,
			76981,
			76983,
			76989,
			76993,
			76995,
			10151,
			80778,
			10551,
			88022,
			14068,
			25833,
			10160,
			87320,
			4497,
			14497,
			48323,
			14100,
			4579,
			11032,
			15671,
			48264,
			11925,
			31627,
			31939,
			12398,
			68261,
			10281,
			68670,
			10745,
			35520,
			35580,
			14535,
			86299,
			86594,
			14493,
			48786,
			17256,
			40872,
			8987,
			16954,
			52788,
			52908,
			10591,
			43467,
			10131,
			86597,
			89654,
			90029,
			8611,
			16690,
			4462,
			13218,
			9100,
			8603,
			18254,
			8673,
			86826,
			15151,
			15032,
			15290,
			14671,
			8700,
			17224,
			18260,
			9284,
			78599,
			78650,
			13394,
			8973,
			86326,
			11763,
			12374,
			35548,
			35620,
			78591,
			78602,
			41276,
			52928,
			78623,
			16067,
			40351,
			40615,
			10918,
			86296,
			11182,
			10700,
			14403,
			58969,
			10133,
			10250,
			86797,
			52795,
			15,
			12737,
			22131,
			12506,
			10291
		],
		"amount": [
			60.0,
			10.0,
			1.0,
			1.0,
			10.0,
			13.0,
			3.0,
			1.0,
			10.0,
			10.0,
			1.0,
			1.0,
			1.0,
			1.0,
			1.0,
			2.0,
			2.0,
			2.0,
			1.0,
			6.0,
			20.0,
			20.0,
			1.0,
			20.0,
			20.0,
			30.0,
			20.0,
			10.0,
			10.0,
			10.0,
			10.0,
			10.0,
			3.0,
			5.0,
			3.0,
			4.0,
			2.0,
			3.0,
			5.0,
			4.0,
			16.0,
			3.0,
			3.0,
			2.0,
			15.0,
			2.0,
			3.0,
			1.0,
			2.0,
			2.0,
			2.0,
			1.0,
			20.0,
			3.0,
			12.0,
			2.0,
			20.0,
			20.0,
			2.0,
			4.0,
			5.0,
			2.0,
			2.0,
			11.0,
			20.0,
			11.0,
			50.0,
			1.0,
			5.0,
			20.0,
			10.0,
			4.0,
			6.0,
			1.0,
			1.0,
			10.0,
			10.0,
			3.0,
			1.0,
			2.0,
			11.0,
			10.0,
			7.0,
			2.0,
			1.0,
			4.0,
			2.0,
			1.0,
			1.0,
			20.0,
			10.0,
			2.0,
			4.0,
			2.0,
			1.0,
			12.0,
			1.0,
			3.0,
			2.0,
			20.0,
			20.0,
			4.0,
			2.0,
			10.0,
			3.0,
			3.0,
			1.0,
			1.0,
			2.0,
			11.0,
			3.0,
			7.0,
			1.0,
			10.0,
			10.0,
			2.0,
			7.0,
			6.0,
			2.0,
			1.0,
			3.0,
			2.0,
			1.0,
			3.0
		],
		"quote_id": [
			10539,
			65,
			36,
			37,
			25,
			56,
			27,
			43,
			61,
			62,
			67,
			68,
			58,
			59,
			49,
			51,
			12,
			39,
			29,
			30,
			24,
			31,
			26,
			40,
			41,
			5295,
			44,
			5001,
			5002,
			5003,
			5004,
			5005,
			528,
			5069,
			674,
			5162,
			1364,
			1981,
			531,
			5158,
			48,
			1460,
			3955,
			1375,
			73,
			871,
			1782,
			3951,
			971,
			2542,
			2566,
			1064,
			4983,
			579,
			4984,
			754,
			3215,
			3224,
			1475,
			5132,
			5144,
			1458,
			3974,
			1964,
			3554,
			324,
			7211,
			4092,
			4100,
			691,
			3578,
			519,
			5145,
			5202,
			5251,
			243,
			1932,
			34,
			1173,
			372,
			239,
			1970,
			256,
			5152,
			1649,
			1622,
			1687,
			1511,
			265,
			1955,
			1971,
			455,
			5020,
			5030,
			1200,
			319,
			5136,
			922,
			1052,
			3220,
			3232,
			5019,
			5021,
			3567,
			4108,
			5025,
			1859,
			3453,
			3532,
			834,
			5131,
			907,
			737,
			1432,
			4316,
			520,
			568,
			5151,
			4094,
			1,
			1111,
			1975,
			1101,
			583
		],
		"supplier": [
			"Enamine",
			"Enamine",
			"Enamine",
			"Enamine",
			"Enamine",
			"Enamine",
			"Enamine",
			"Enamine",
			"Enamine",
			"Enamine",
			"Enamine",
			"Enamine",
			"Enamine",
			"Enamine",
			"Enamine",
			"Enamine",
			"Enamine",
			"Enamine",
			"Enamine",
			"Enamine",
			"Enamine",
			"Enamine",
			"Enamine",
			"Enamine",
			"Enamine",
			"Enamine",
			"Enamine",
			"Enamine",
			"Enamine",
			"Enamine",
			"Enamine",
			"Enamine",
			[
				"Stock",
				"Enamine"
			],
			[
				"Stock",
				"Enamine"
			],
			[
				"Stock",
				"Enamine"
			],
			[
				"Stock",
				"Enamine"
			],
			[
				"Stock",
				"Enamine"
			],
			[
				"Stock",
				"Enamine"
			],
			[
				"Stock",
				"Enamine"
			],
			[
				"Stock",
				"Enamine"
			],
			[
				"Stock",
				"Enamine"
			],
			[
				"Stock",
				"Enamine"
			],
			[
				"Stock",
				"Enamine"
			],
			[
				"Stock",
				"Enamine"
			],
			[
				"Stock",
				"Enamine"
			],
			[
				"Stock",
				"Enamine"
			],
			[
				"Stock",
				"Enamine"
			],
			[
				"Stock",
				"Enamine"
			],
			[
				"Stock",
				"Enamine"
			],
			[
				"Stock",
				"Enamine"
			],
			[
				"Stock",
				"Enamine"
			],
			[
				"Stock",
				"Enamine"
			],
			[
				"Stock",
				"Enamine"
			],
			[
				"Stock",
				"Enamine"
			],
			[
				"Stock",
				"Enamine"
			],
			[
				"Stock",
				"Enamine"
			],
			[
				"Stock",
				"Enamine"
			],
			[
				"Stock",
				"Enamine"
			],
			[
				"Stock",
				"Enamine"
			],
			[
				"Stock",
				"Enamine"
			],
			[
				"Stock",
				"Enamine"
			],
			[
				"Stock",
				"Enamine"
			],
			[
				"Stock",
				"Enamine"
			],
			[
				"Stock",
				"Enamine"
			],
			[
				"Stock",
				"Enamine"
			],
			[
				"Stock",
				"Enamine"
			],
			[
				"Stock",
				"Enamine"
			],
			[
				"Stock",
				"Enamine"
			],
			[
				"Stock",
				"Enamine"
			],
			[
				"Stock",
				"Enamine"
			],
			[
				"Stock",
				"Enamine"
			],
			[
				"Stock",
				"Enamine"
			],
			[
				"Stock",
				"Enamine"
			],
			[
				"Stock",
				"Enamine"
			],
			[
				"Stock",
				"Enamine"
			],
			[
				"Stock",
				"Enamine"
			],
			[
				"Stock",
				"Enamine"
			],
			[
				"Stock",
				"Enamine"
			],
			[
				"Stock",
				"Enamine"
			],
			[
				"Stock",
				"Enamine"
			],
			[
				"Stock",
				"Enamine"
			],
			[
				"Stock",
				"Enamine"
			],
			[
				"Stock",
				"Enamine"
			],
			[
				"Stock",
				"Enamine"
			],
			[
				"Stock",
				"Enamine"
			],
			[
				"Stock",
				"Enamine"
			],
			[
				"Stock",
				"Enamine"
			],
			[
				"Stock",
				"Enamine"
			],
			[
				"Stock",
				"Enamine"
			],
			[
				"Stock",
				"Enamine"
			],
			[
				"Stock",
				"Enamine"
			],
			[
				"Stock",
				"Enamine"
			],
			[
				"Stock",
				"Enamine"
			],
			[
				"Stock",
				"Enamine"
			],
			[
				"Stock",
				"Enamine"
			],
			[
				"Stock",
				"Enamine"
			],
			[
				"Stock",
				"Enamine"
			],
			[
				"Stock",
				"Enamine"
			],
			[
				"Stock",
				"Enamine"
			],
			[
				"Stock",
				"Enamine"
			],
			[
				"Stock",
				"Enamine"
			],
			[
				"Stock",
				"Enamine"
			],
			[
				"Stock",
				"Enamine"
			],
			[
				"Stock",
				"Enamine"
			],
			[
				"Stock",
				"Enamine"
			],
			[
				"Stock",
				"Enamine"
			],
			[
				"Stock",
				"Enamine"
			],
			[
				"Stock",
				"Enamine"
			],
			[
				"Stock",
				"Enamine"
			],
			[
				"Stock",
				"Enamine"
			],
			[
				"Stock",
				"Enamine"
			],
			[
				"Stock",
				"Enamine"
			],
			[
				"Stock",
				"Enamine"
			],
			[
				"Stock",
				"Enamine"
			],
			[
				"Stock",
				"Enamine"
			],
			[
				"Stock",
				"Enamine"
			],
			[
				"Stock",
				"Enamine"
			],
			[
				"Stock",
				"Enamine"
			],
			[
				"Stock",
				"Enamine"
			],
			[
				"Stock",
				"Enamine"
			],
			[
				"Stock",
				"Enamine"
			],
			[
				"Stock",
				"Enamine"
			],
			[
				"Stock",
				"Enamine"
			],
			[
				"Stock",
				"Enamine"
			]
		],
		"max_lead_time": [
			null,
			null,
			null,
			null,
			null,
			null,
			null,
			null,
			null,
			null,
			null,
			null,
			null,
			null,
			null,
			null,
			null,
			null,
			null,
			null,
			null,
			null,
			null,
			null,
			null,
			null,
			null,
			null,
			null,
			null,
			null,
			null,
			null,
			null,
			null,
			null,
			null,
			null,
			null,
			null,
			null,
			null,
			null,
			null,
			null,
			null,
			null,
			null,
			null,
			null,
			null,
			null,
			null,
			null,
			null,
			null,
			null,
			null,
			null,
			null,
			null,
			null,
			null,
			null,
			null,
			null,
			null,
			null,
			null,
			null,
			null,
			null,
			null,
			null,
			null,
			null,
			null,
			null,
			null,
			null,
			null,
			null,
			null,
			null,
			null,
			null,
			null,
			null,
			null,
			null,
			null,
			null,
			null,
			null,
			null,
			null,
			null,
			null,
			null,
			null,
			null,
			null,
			null,
			null,
			null,
			null,
			null,
			null,
			null,
			null,
			null,
			null,
			null,
			null,
			null,
			null,
			null,
			null,
			null,
			null,
			null,
			null,
			null,
			null
		],
		"quoted_amount": [
			100.0,
			20.0,
			20.0,
			20.0,
			20.0,
			20.0,
			20.0,
			20.0,
			20.0,
			20.0,
			20.0,
			20.0,
			20.0,
			20.0,
			20.0,
			20.0,
			20.0,
			20.0,
			20.0,
			20.0,
			20.0,
			20.0,
			20.0,
			20.0,
			20.0,
			50.0,
			20.0,
			20.0,
			20.0,
			20.0,
			20.0,
			20.0,
			20.0,
			20.0,
			20.0,
			20.0,
			20.0,
			20.0,
			20.0,
			20.0,
			20.0,
			20.0,
			20.0,
			20.0,
			20.0,
			20.0,
			20.0,
			20.0,
			20.0,
			20.0,
			20.0,
			20.0,
			20.0,
			20.0,
			20.0,
			20.0,
			20.0,
			20.0,
			20.0,
			20.0,
			20.0,
			20.0,
			20.0,
			20.0,
			20.0,
			20.0,
			50.0,
			20.0,
			20.0,
			20.0,
			20.0,
			20.0,
			20.0,
			20.0,
			20.0,
			20.0,
			20.0,
			20.0,
			20.0,
			20.0,
			20.0,
			20.0,
			20.0,
			20.0,
			20.0,
			20.0,
			20.0,
			20.0,
			20.0,
			20.0,
			20.0,
			20.0,
			20.0,
			20.0,
			20.0,
			20.0,
			20.0,
			20.0,
			20.0,
			20.0,
			20.0,
			20.0,
			20.0,
			20.0,
			20.0,
			20.0,
			20.0,
			20.0,
			20.0,
			20.0,
			20.0,
			20.0,
			20.0,
			20.0,
			20.0,
			20.0,
			20.0,
			20.0,
			20.0,
			20.0,
			20.0,
			20.0,
			20.0,
			20.0
		]
	},
	"intermediates": {
		"compound_id": [
			48256,
			48415,
			48549,
			48252
		],
		"amount": [
			2.0,
			2.0,
			1.0,
			1.0
		],
		"quote_id": [
			null,
			null,
			null,
			null
		],
		"supplier": [
			null,
			null,
			null,
			null
		],
		"max_lead_time": [
			null,
			null,
			null,
			null
		],
		"quoted_amount": [
			null,
			null,
			null,
			null
		]
	},
	"products": {
		"compound_id": [
			93,
			95,
			104,
			796,
			1001,
			1128,
			1316,
			1473,
			1917,
			2916,
			2925,
			3284,
			3624,
			3625,
			3628,
			76982,
			76984,
			76990,
			76994,
			76996,
			89341,
			89218,
			27209,
			88381,
			48958,
			27243,
			11351,
			49161,
			12741,
			32082,
			72628,
			71505,
			71897,
			35663,
			49859,
			86889,
			49557,
			43008,
			82712,
			53056,
			45230,
			86903,
			90654,
			81492,
			25842,
			9940,
			83149,
			86835,
			15152,
			16514,
			14672,
			68913,
			20471,
			69685,
			78806,
			26453,
			83013,
			86953,
			72285,
			72694,
			67900,
			78779,
			41277,
			80057,
			16068,
			40661,
			19146,
			87114,
			70718,
			71034,
			59812,
			71452,
			88037,
			53175,
			12736,
			22341,
			12804,
			68853,
			15672,
			87113,
			79877,
			31940,
			71500,
			78734,
			88391,
			35521,
			69602,
			69233,
			88055,
			89164,
			78781,
			89358,
			89146,
			89276,
			41764,
			27004,
			12738,
			11847,
			81560,
			22307,
			88093,
			49600,
			68854,
			9953,
			53151,
			70493,
			35845,
			78786,
			19150,
			11274,
			72020,
			80002,
			89266,
			49639,
			70691,
			72446,
			72226,
			70299,
			10055,
			15108,
			86983,
			87116,
			31628,
			88023,
			67845,
			78740,
			14536,
			88095,
			87117,
			72546,
			70467,
			88350,
			70492,
			88425,
			79935,
			12148,
			69780,
			26877,
			69987,
			78732,
			71645,
			71082,
			11444,
			86617,
			86873,
			88132,
			69973,
			69793,
			87086,
			79807,
			12761,
			70506,
			89264,
			40616,
			43012,
			70285,
			89301,
			11401,
			11611,
			15291,
			15114,
			88271
		],
		"amount": [
			1,
			1,
			1,
			1,
			1,
			1,
			1,
			1,
			1,
			1,
			1,
			1,
			1,
			1,
			1,
			1,
			1,
			1,
			1,
			1,
			1,
			1,
			1,
			1,
			1,
			1,
			1,
			1,
			1,
			1,
			1,
			1,
			1,
			1,
			1,
			1,
			1,
			1,
			1,
			1,
			1,
			1,
			1,
			1,
			1,
			1,
			1,
			1,
			1,
			1,
			1,
			1,
			1,
			1,
			1,
			1,
			1,
			1,
			1,
			1,
			1,
			1,
			1,
			1,
			1,
			1,
			1,
			1,
			1,
			1,
			1,
			1,
			1,
			1,
			1,
			1,
			1,
			1,
			1,
			1,
			1,
			1,
			1,
			1,
			1,
			1,
			1,
			1,
			1,
			1,
			1,
			1,
			1,
			1,
			1,
			1,
			1,
			1,
			1,
			1,
			1,
			1,
			1,
			1,
			1,
			1,
			1,
			1,
			1,
			1,
			1,
			1,
			1,
			1,
			1,
			1,
			1,
			1,
			1,
			1,
			1,
			1,
			1,
			1,
			1,
			1,
			1,
			1,
			1,
			1,
			1,
			1,
			1,
			1,
			1,
			1,
			1,
			1,
			1,
			1,
			1,
			1,
			1,
			1,
			1,
			1,
			1,
			1,
			1,
			1,
			1,
			1,
			1,
			1,
			1,
			1,
			1,
			1,
			1,
			1,
			1,
			1
		],
		"quote_id": [
			null,
			null,
			null,
			null,
			null,
			null,
			null,
			null,
			null,
			null,
			null,
			null,
			null,
			null,
			null,
			null,
			null,
			null,
			null,
			null,
			null,
			null,
			null,
			null,
			null,
			null,
			null,
			null,
			null,
			null,
			null,
			null,
			null,
			null,
			null,
			null,
			null,
			null,
			null,
			null,
			null,
			null,
			null,
			null,
			null,
			null,
			null,
			null,
			null,
			null,
			null,
			null,
			null,
			null,
			null,
			null,
			null,
			null,
			null,
			null,
			null,
			null,
			null,
			null,
			null,
			null,
			null,
			null,
			null,
			null,
			null,
			null,
			null,
			null,
			null,
			null,
			null,
			null,
			null,
			null,
			null,
			null,
			null,
			null,
			null,
			null,
			null,
			null,
			null,
			null,
			null,
			null,
			null,
			null,
			null,
			null,
			null,
			null,
			null,
			null,
			null,
			null,
			null,
			null,
			null,
			null,
			null,
			null,
			null,
			null,
			null,
			null,
			null,
			null,
			null,
			null,
			null,
			null,
			null,
			null,
			null,
			null,
			null,
			null,
			null,
			null,
			null,
			null,
			null,
			null,
			null,
			null,
			null,
			null,
			null,
			null,
			null,
			null,
			null,
			null,
			null,
			null,
			null,
			null,
			null,
			null,
			null,
			null,
			null,
			null,
			null,
			null,
			null,
			null,
			null,
			null,
			null,
			null,
			null,
			null,
			null,
			null
		],
		"supplier": [
			null,
			null,
			null,
			null,
			null,
			null,
			null,
			null,
			null,
			null,
			null,
			null,
			null,
			null,
			null,
			null,
			null,
			null,
			null,
			null,
			null,
			null,
			null,
			null,
			null,
			null,
			null,
			null,
			null,
			null,
			null,
			null,
			null,
			null,
			null,
			null,
			null,
			null,
			null,
			null,
			null,
			null,
			null,
			null,
			null,
			null,
			null,
			null,
			null,
			null,
			null,
			null,
			null,
			null,
			null,
			null,
			null,
			null,
			null,
			null,
			null,
			null,
			null,
			null,
			null,
			null,
			null,
			null,
			null,
			null,
			null,
			null,
			null,
			null,
			null,
			null,
			null,
			null,
			null,
			null,
			null,
			null,
			null,
			null,
			null,
			null,
			null,
			null,
			null,
			null,
			null,
			null,
			null,
			null,
			null,
			null,
			null,
			null,
			null,
			null,
			null,
			null,
			null,
			null,
			null,
			null,
			null,
			null,
			null,
			null,
			null,
			null,
			null,
			null,
			null,
			null,
			null,
			null,
			null,
			null,
			null,
			null,
			null,
			null,
			null,
			null,
			null,
			null,
			null,
			null,
			null,
			null,
			null,
			null,
			null,
			null,
			null,
			null,
			null,
			null,
			null,
			null,
			null,
			null,
			null,
			null,
			null,
			null,
			null,
			null,
			null,
			null,
			null,
			null,
			null,
			null,
			null,
			null,
			null,
			null,
			null,
			null
		],
		"max_lead_time": [
			null,
			null,
			null,
			null,
			null,
			null,
			null,
			null,
			null,
			null,
			null,
			null,
			null,
			null,
			null,
			null,
			null,
			null,
			null,
			null,
			null,
			null,
			null,
			null,
			null,
			null,
			null,
			null,
			null,
			null,
			null,
			null,
			null,
			null,
			null,
			null,
			null,
			null,
			null,
			null,
			null,
			null,
			null,
			null,
			null,
			null,
			null,
			null,
			null,
			null,
			null,
			null,
			null,
			null,
			null,
			null,
			null,
			null,
			null,
			null,
			null,
			null,
			null,
			null,
			null,
			null,
			null,
			null,
			null,
			null,
			null,
			null,
			null,
			null,
			null,
			null,
			null,
			null,
			null,
			null,
			null,
			null,
			null,
			null,
			null,
			null,
			null,
			null,
			null,
			null,
			null,
			null,
			null,
			null,
			null,
			null,
			null,
			null,
			null,
			null,
			null,
			null,
			null,
			null,
			null,
			null,
			null,
			null,
			null,
			null,
			null,
			null,
			null,
			null,
			null,
			null,
			null,
			null,
			null,
			null,
			null,
			null,
			null,
			null,
			null,
			null,
			null,
			null,
			null,
			null,
			null,
			null,
			null,
			null,
			null,
			null,
			null,
			null,
			null,
			null,
			null,
			null,
			null,
			null,
			null,
			null,
			null,
			null,
			null,
			null,
			null,
			null,
			null,
			null,
			null,
			null,
			null,
			null,
			null,
			null,
			null,
			null
		],
		"quoted_amount": [
			null,
			null,
			null,
			null,
			null,
			null,
			null,
			null,
			null,
			null,
			null,
			null,
			null,
			null,
			null,
			null,
			null,
			null,
			null,
			null,
			null,
			null,
			null,
			null,
			null,
			null,
			null,
			null,
			null,
			null,
			null,
			null,
			null,
			null,
			null,
			null,
			null,
			null,
			null,
			null,
			null,
			null,
			null,
			null,
			null,
			null,
			null,
			null,
			null,
			null,
			null,
			null,
			null,
			null,
			null,
			null,
			null,
			null,
			null,
			null,
			null,
			null,
			null,
			null,
			null,
			null,
			null,
			null,
			null,
			null,
			null,
			null,
			null,
			null,
			null,
			null,
			null,
			null,
			null,
			null,
			null,
			null,
			null,
			null,
			null,
			null,
			null,
			null,
			null,
			null,
			null,
			null,
			null,
			null,
			null,
			null,
			null,
			null,
			null,
			null,
			null,
			null,
			null,
			null,
			null,
			null,
			null,
			null,
			null,
			null,
			null,
			null,
			null,
			null,
			null,
			null,
			null,
			null,
			null,
			null,
			null,
			null,
			null,
			null,
			null,
			null,
			null,
			null,
			null,
			null,
			null,
			null,
			null,
			null,
			null,
			null,
			null,
			null,
			null,
			null,
			null,
			null,
			null,
			null,
			null,
			null,
			null,
			null,
			null,
			null,
			null,
			null,
			null,
			null,
			null,
			null,
			null,
			null,
			null,
			null,
			null,
			null
		]
	},
	"reaction_ids": [
		14,
		77327,
		17,
		18,
		57873,
		75798,
		38426,
		29,
		33,
		8738,
		35,
		37,
		69670,
		55334,
		54309,
		75816,
		25641,
		43,
		37420,
		56888,
		29754,
		61,
		7743,
		38464,
		57921,
		7749,
		57926,
		58440,
		65096,
		65098,
		56394,
		65105,
		82,
		56914,
		56913,
		85,
		58966,
		18007,
		56408,
		7772,
		29788,
		94,
		56927,
		74845,
		19042,
		103,
		105,
		108,
		32364,
		57455,
		32368,
		69233,
		38002,
		5238,
		11385,
		5754,
		11389,
		73343,
		65151,
		65153,
		23171,
		65160,
		75927,
		57503,
		65189,
		7845,
		59048,
		74924,
		8373,
		73399,
		18618,
		5314,
		14530,
		75973,
		75975,
		74954,
		73421,
		75985,
		58066,
		66259,
		74964,
		56023,
		73435,
		19169,
		14563,
		59114,
		76010,
		5364,
		74998,
		7418,
		23307,
		73487,
		76050,
		38677,
		58646,
		37144,
		25369,
		6426,
		66330,
		37148,
		6427,
		6430,
		57112,
		5407,
		76067,
		56106,
		5930,
		73517,
		6448,
		57139,
		7490,
		4421,
		58705,
		4434,
		30549,
		66390,
		6487,
		67928,
		55654,
		74598,
		31089,
		22899,
		74612,
		47990,
		56706,
		25476,
		74630,
		41353,
		56201,
		63375,
		63376,
		56720,
		63379,
		63381,
		63382,
		56214,
		34713,
		8091,
		66459,
		69534,
		12704,
		73634,
		37286,
		37802,
		68012,
		74668,
		19374,
		74670,
		73133,
		4536,
		5572,
		58318,
		19408,
		74707,
		66516,
		73685,
		73684,
		73687,
		73688,
		41438,
		55274,
		55275,
		54251,
		38383,
		41457,
		58866
	],
	"rgen_data_path": "/opt/xchem-fragalysis-2/maxwin/CHIKV_HIPPO/hippo_prod/CHIKV_prod8b_rgen.json",
	"rgen_db_path": "/opt/xchem-fragalysis-2/maxwin/CHIKV_HIPPO/hippo_prod/CHIKV_prod8b.sqlite",
	"rgen_recipe_dir": "/opt/xchem-fragalysis-2/maxwin/CHIKV_HIPPO/hippo_prod/CHIKV_prod8b_recipes",
	"rgen_max_lead_time": null,
	"rgen_suppliers": [
		"Stock",
		"Enamine"
	],
	"gen_budget": 10000,
	"gen_currency": "EUR",
	"gen_max_products": 1200,
	"gen_max_reactions": 3000,
	"gen_max_iter": 5000,
	"gen_shuffle": true,
	"gen_iterations": 4999,
	"gen_stop_reason": "Max #iterations reached",
	"gen_recipe_path": "/opt/xchem-fragalysis-2/maxwin/CHIKV_HIPPO/hippo_prod/CHIKV_prod8b_recipes/Recipe_1GD9PCV.json"
}