{
	"database": "/opt/xchem-fragalysis-2/maxwin/CHIKV_HIPPO/hippo_prod/CHIKV_prod9b.sqlite",
	"timestamp": "2024-10-14 15:04:29.543564",
	"price": {
		"amount": 10993.0,
		"currency": "EUR"
	},
	"reactant_supplier": [
		"Stock",
		"Enamine"
	],
	"reactants": {
		"compound_id": [
			85,
			4554,
			4466,
			4467,
			4440,
			4530,
			4445,
			4480,
			4545,
			4546,
			4557,
			4558,
			4534,
			4535,
			4505,
			4507,
			84,
			4472,
			4449,
			4450,
			4439,
			4451,
			4444,
			4476,
			4477,
			4452,
			4483,
			76981,
			76983,
			76989,
			76993,
			76995,
			35555,
			35586,
			16829,
			41774,
			35620,
			36120,
			11911,
			68670,
			86299,
			86571,
			14839,
			37900,
			77062,
			4579,
			11767,
			16731,
			17260,
			31629,
			31661,
			62995,
			63667,
			29439,
			11789,
			10348,
			68261,
			53216,
			78576,
			17256,
			40927,
			4497,
			14515,
			48323,
			9347,
			10729,
			40982,
			63049,
			63078,
			37786,
			39289,
			16776,
			43499,
			8953,
			16954,
			79223,
			11870,
			15671,
			49646,
			9126,
			18254,
			11096,
			8955,
			35694,
			36021,
			9136,
			22114,
			10144,
			87314,
			8592,
			11114,
			40961,
			13261,
			25833,
			8945,
			10540,
			40872,
			16288,
			14010,
			63116,
			11919,
			11905,
			37610,
			77003,
			13147,
			58969,
			17220,
			8702,
			35538,
			35598,
			10682,
			87461,
			37666,
			10142,
			86695,
			4618,
			8584,
			16640,
			17252,
			14503,
			14545,
			11803,
			17218,
			72797,
			10095,
			13706,
			10922,
			40914,
			52926,
			78650,
			17214,
			40866,
			17222,
			86282,
			78636,
			40363,
			10170,
			37191,
			9294,
			10634,
			4462,
			13486,
			52780,
			53492,
			86326,
			86614,
			9260,
			53434,
			10129
		],
		"amount": [
			60.0,
			10.0,
			2.0,
			1.0,
			12.0,
			11.0,
			2.0,
			2.0,
			10.0,
			10.0,
			1.0,
			1.0,
			2.0,
			2.0,
			2.0,
			6.0,
			1.0,
			1.0,
			3.0,
			3.0,
			21.0,
			20.0,
			1.0,
			31.0,
			20.0,
			32.0,
			30.0,
			10.0,
			10.0,
			10.0,
			10.0,
			10.0,
			20.0,
			20.0,
			20.0,
			20.0,
			20.0,
			10.0,
			3.0,
			17.0,
			6.0,
			4.0,
			2.0,
			2.0,
			2.0,
			16.0,
			1.0,
			20.0,
			10.0,
			1.0,
			1.0,
			2.0,
			1.0,
			1.0,
			1.0,
			2.0,
			11.0,
			1.0,
			3.0,
			10.0,
			20.0,
			5.0,
			2.0,
			3.0,
			3.0,
			20.0,
			20.0,
			1.0,
			3.0,
			3.0,
			1.0,
			20.0,
			20.0,
			12.0,
			20.0,
			2.0,
			1.0,
			1.0,
			1.0,
			10.0,
			20.0,
			2.0,
			11.0,
			20.0,
			20.0,
			4.0,
			4.0,
			3.0,
			2.0,
			11.0,
			11.0,
			20.0,
			1.0,
			3.0,
			1.0,
			13.0,
			20.0,
			1.0,
			2.0,
			3.0,
			1.0,
			3.0,
			1.0,
			1.0,
			10.0,
			10.0,
			11.0,
			1.0,
			20.0,
			20.0,
			3.0,
			4.0,
			2.0,
			3.0,
			2.0,
			1.0,
			10.0,
			20.0,
			20.0,
			4.0,
			2.0,
			2.0,
			1.0,
			5.0,
			2.0,
			2.0,
			41.0,
			20.0,
			3.0,
			2.0,
			10.0,
			20.0,
			10.0,
			2.0,
			2.0,
			1.0,
			20.0,
			20.0,
			2.0,
			1.0,
			3.0,
			1.0,
			4.0,
			1.0,
			1.0,
			3.0,
			1.0,
			1.0,
			2.0
		],
		"quote_id": [
			10539,
			65,
			36,
			37,
			25,
			56,
			27,
			43,
			61,
			62,
			67,
			68,
			58,
			59,
			49,
			51,
			12,
			39,
			29,
			30,
			5287,
			31,
			26,
			5303,
			41,
			5295,
			5307,
			5001,
			5002,
			5003,
			5004,
			5005,
			3221,
			3227,
			1944,
			3572,
			3232,
			3252,
			966,
			4984,
			5132,
			5143,
			1572,
			3358,
			5009,
			73,
			924,
			1933,
			1966,
			2543,
			2549,
			4870,
			4955,
			2220,
			934,
			596,
			4983,
			4126,
			5015,
			1964,
			3559,
			48,
			1466,
			3955,
			485,
			746,
			3562,
			4887,
			4892,
			3327,
			3422,
			1939,
			3580,
			310,
			1948,
			5047,
			952,
			1782,
			3994,
			385,
			1970,
			884,
			311,
			3238,
			3249,
			390,
			1974,
			525,
			5157,
			234,
			892,
			3561,
			1180,
			1981,
			306,
			670,
			3554,
			1920,
			1346,
			4901,
			969,
			963,
			3286,
			5006,
			1157,
			4316,
			1953,
			266,
			3219,
			3228,
			730,
			5159,
			3305,
			524,
			5148,
			78,
			230,
			1931,
			1963,
			1462,
			1478,
			935,
			1952,
			4988,
			507,
			1253,
			6099,
			3558,
			4107,
			5030,
			1950,
			3553,
			1954,
			5129,
			5028,
			3455,
			534,
			3262,
			460,
			712,
			34,
			1213,
			4090,
			4147,
			5136,
			5146,
			444,
			4129,
			518
		],
		"supplier": [
			"Enamine",
			"Enamine",
			"Enamine",
			"Enamine",
			"Enamine",
			"Enamine",
			"Enamine",
			"Enamine",
			"Enamine",
			"Enamine",
			"Enamine",
			"Enamine",
			"Enamine",
			"Enamine",
			"Enamine",
			"Enamine",
			"Enamine",
			"Enamine",
			"Enamine",
			"Enamine",
			"Enamine",
			"Enamine",
			"Enamine",
			"Enamine",
			"Enamine",
			"Enamine",
			"Enamine",
			"Enamine",
			"Enamine",
			"Enamine",
			"Enamine",
			"Enamine",
			[
				"Stock",
				"Enamine"
			],
			[
				"Stock",
				"Enamine"
			],
			[
				"Stock",
				"Enamine"
			],
			[
				"Stock",
				"Enamine"
			],
			[
				"Stock",
				"Enamine"
			],
			[
				"Stock",
				"Enamine"
			],
			[
				"Stock",
				"Enamine"
			],
			[
				"Stock",
				"Enamine"
			],
			[
				"Stock",
				"Enamine"
			],
			[
				"Stock",
				"Enamine"
			],
			[
				"Stock",
				"Enamine"
			],
			[
				"Stock",
				"Enamine"
			],
			[
				"Stock",
				"Enamine"
			],
			[
				"Stock",
				"Enamine"
			],
			[
				"Stock",
				"Enamine"
			],
			[
				"Stock",
				"Enamine"
			],
			[
				"Stock",
				"Enamine"
			],
			[
				"Stock",
				"Enamine"
			],
			[
				"Stock",
				"Enamine"
			],
			[
				"Stock",
				"Enamine"
			],
			[
				"Stock",
				"Enamine"
			],
			[
				"Stock",
				"Enamine"
			],
			[
				"Stock",
				"Enamine"
			],
			[
				"Stock",
				"Enamine"
			],
			[
				"Stock",
				"Enamine"
			],
			[
				"Stock",
				"Enamine"
			],
			[
				"Stock",
				"Enamine"
			],
			[
				"Stock",
				"Enamine"
			],
			[
				"Stock",
				"Enamine"
			],
			[
				"Stock",
				"Enamine"
			],
			[
				"Stock",
				"Enamine"
			],
			[
				"Stock",
				"Enamine"
			],
			[
				"Stock",
				"Enamine"
			],
			[
				"Stock",
				"Enamine"
			],
			[
				"Stock",
				"Enamine"
			],
			[
				"Stock",
				"Enamine"
			],
			[
				"Stock",
				"Enamine"
			],
			[
				"Stock",
				"Enamine"
			],
			[
				"Stock",
				"Enamine"
			],
			[
				"Stock",
				"Enamine"
			],
			[
				"Stock",
				"Enamine"
			],
			[
				"Stock",
				"Enamine"
			],
			[
				"Stock",
				"Enamine"
			],
			[
				"Stock",
				"Enamine"
			],
			[
				"Stock",
				"Enamine"
			],
			[
				"Stock",
				"Enamine"
			],
			[
				"Stock",
				"Enamine"
			],
			[
				"Stock",
				"Enamine"
			],
			[
				"Stock",
				"Enamine"
			],
			[
				"Stock",
				"Enamine"
			],
			[
				"Stock",
				"Enamine"
			],
			[
				"Stock",
				"Enamine"
			],
			[
				"Stock",
				"Enamine"
			],
			[
				"Stock",
				"Enamine"
			],
			[
				"Stock",
				"Enamine"
			],
			[
				"Stock",
				"Enamine"
			],
			[
				"Stock",
				"Enamine"
			],
			[
				"Stock",
				"Enamine"
			],
			[
				"Stock",
				"Enamine"
			],
			[
				"Stock",
				"Enamine"
			],
			[
				"Stock",
				"Enamine"
			],
			[
				"Stock",
				"Enamine"
			],
			[
				"Stock",
				"Enamine"
			],
			[
				"Stock",
				"Enamine"
			],
			[
				"Stock",
				"Enamine"
			],
			[
				"Stock",
				"Enamine"
			],
			[
				"Stock",
				"Enamine"
			],
			[
				"Stock",
				"Enamine"
			],
			[
				"Stock",
				"Enamine"
			],
			[
				"Stock",
				"Enamine"
			],
			[
				"Stock",
				"Enamine"
			],
			[
				"Stock",
				"Enamine"
			],
			[
				"Stock",
				"Enamine"
			],
			[
				"Stock",
				"Enamine"
			],
			[
				"Stock",
				"Enamine"
			],
			[
				"Stock",
				"Enamine"
			],
			[
				"Stock",
				"Enamine"
			],
			[
				"Stock",
				"Enamine"
			],
			[
				"Stock",
				"Enamine"
			],
			[
				"Stock",
				"Enamine"
			],
			[
				"Stock",
				"Enamine"
			],
			[
				"Stock",
				"Enamine"
			],
			[
				"Stock",
				"Enamine"
			],
			[
				"Stock",
				"Enamine"
			],
			[
				"Stock",
				"Enamine"
			],
			[
				"Stock",
				"Enamine"
			],
			[
				"Stock",
				"Enamine"
			],
			[
				"Stock",
				"Enamine"
			],
			[
				"Stock",
				"Enamine"
			],
			[
				"Stock",
				"Enamine"
			],
			[
				"Stock",
				"Enamine"
			],
			[
				"Stock",
				"Enamine"
			],
			[
				"Stock",
				"Enamine"
			],
			[
				"Stock",
				"Enamine"
			],
			[
				"Stock",
				"Enamine"
			],
			[
				"Stock",
				"Enamine"
			],
			[
				"Stock",
				"Enamine"
			],
			[
				"Stock",
				"Enamine"
			],
			[
				"Stock",
				"Enamine"
			],
			[
				"Stock",
				"Enamine"
			],
			[
				"Stock",
				"Enamine"
			],
			[
				"Stock",
				"Enamine"
			],
			[
				"Stock",
				"Enamine"
			],
			[
				"Stock",
				"Enamine"
			],
			[
				"Stock",
				"Enamine"
			],
			[
				"Stock",
				"Enamine"
			],
			[
				"Stock",
				"Enamine"
			],
			[
				"Stock",
				"Enamine"
			],
			[
				"Stock",
				"Enamine"
			],
			[
				"Stock",
				"Enamine"
			],
			[
				"Stock",
				"Enamine"
			],
			[
				"Stock",
				"Enamine"
			],
			[
				"Stock",
				"Enamine"
			],
			[
				"Stock",
				"Enamine"
			],
			[
				"Stock",
				"Enamine"
			],
			[
				"Stock",
				"Enamine"
			],
			[
				"Stock",
				"Enamine"
			]
		],
		"max_lead_time": [
			null,
			null,
			null,
			null,
			null,
			null,
			null,
			null,
			null,
			null,
			null,
			null,
			null,
			null,
			null,
			null,
			null,
			null,
			null,
			null,
			null,
			null,
			null,
			null,
			null,
			null,
			null,
			null,
			null,
			null,
			null,
			null,
			null,
			null,
			null,
			null,
			null,
			null,
			null,
			null,
			null,
			null,
			null,
			null,
			null,
			null,
			null,
			null,
			null,
			null,
			null,
			null,
			null,
			null,
			null,
			null,
			null,
			null,
			null,
			null,
			null,
			null,
			null,
			null,
			null,
			null,
			null,
			null,
			null,
			null,
			null,
			null,
			null,
			null,
			null,
			null,
			null,
			null,
			null,
			null,
			null,
			null,
			null,
			null,
			null,
			null,
			null,
			null,
			null,
			null,
			null,
			null,
			null,
			null,
			null,
			null,
			null,
			null,
			null,
			null,
			null,
			null,
			null,
			null,
			null,
			null,
			null,
			null,
			null,
			null,
			null,
			null,
			null,
			null,
			null,
			null,
			null,
			null,
			null,
			null,
			null,
			null,
			null,
			null,
			null,
			null,
			null,
			null,
			null,
			null,
			null,
			null,
			null,
			null,
			null,
			null,
			null,
			null,
			null,
			null,
			null,
			null,
			null,
			null,
			null,
			null,
			null,
			null,
			null
		],
		"quoted_amount": [
			100.0,
			20.0,
			20.0,
			20.0,
			20.0,
			20.0,
			20.0,
			20.0,
			20.0,
			20.0,
			20.0,
			20.0,
			20.0,
			20.0,
			20.0,
			20.0,
			20.0,
			20.0,
			20.0,
			20.0,
			50.0,
			20.0,
			20.0,
			50.0,
			20.0,
			50.0,
			50.0,
			20.0,
			20.0,
			20.0,
			20.0,
			20.0,
			20.0,
			20.0,
			20.0,
			20.0,
			20.0,
			20.0,
			20.0,
			20.0,
			20.0,
			20.0,
			20.0,
			20.0,
			20.0,
			20.0,
			20.0,
			20.0,
			20.0,
			20.0,
			20.0,
			20.0,
			20.0,
			20.0,
			20.0,
			20.0,
			20.0,
			20.0,
			20.0,
			20.0,
			20.0,
			20.0,
			20.0,
			20.0,
			20.0,
			20.0,
			20.0,
			20.0,
			20.0,
			20.0,
			20.0,
			20.0,
			20.0,
			20.0,
			20.0,
			20.0,
			20.0,
			20.0,
			20.0,
			20.0,
			20.0,
			20.0,
			20.0,
			20.0,
			20.0,
			20.0,
			20.0,
			20.0,
			20.0,
			20.0,
			20.0,
			20.0,
			20.0,
			20.0,
			20.0,
			20.0,
			20.0,
			20.0,
			20.0,
			20.0,
			20.0,
			20.0,
			20.0,
			20.0,
			20.0,
			20.0,
			20.0,
			20.0,
			20.0,
			20.0,
			20.0,
			20.0,
			20.0,
			20.0,
			20.0,
			20.0,
			20.0,
			20.0,
			20.0,
			20.0,
			20.0,
			20.0,
			20.0,
			20.0,
			20.0,
			20.0,
			50.0,
			20.0,
			20.0,
			20.0,
			20.0,
			20.0,
			20.0,
			20.0,
			20.0,
			20.0,
			20.0,
			20.0,
			20.0,
			20.0,
			20.0,
			20.0,
			20.0,
			20.0,
			20.0,
			20.0,
			20.0,
			20.0,
			20.0
		]
	},
	"intermediates": {
		"compound_id": [
			48412,
			48415,
			48449,
			4498
		],
		"amount": [
			1.0,
			1.0,
			1.0,
			1.0
		],
		"quote_id": [
			null,
			null,
			null,
			null
		],
		"supplier": [
			null,
			null,
			null,
			null
		],
		"max_lead_time": [
			null,
			null,
			null,
			null
		],
		"quoted_amount": [
			null,
			null,
			null,
			null
		]
	},
	"products": {
		"compound_id": [
			93,
			95,
			104,
			796,
			1001,
			1128,
			1316,
			1473,
			1917,
			2916,
			2925,
			3284,
			3624,
			3625,
			3628,
			76982,
			76984,
			76990,
			76994,
			76996,
			35795,
			44898,
			68009,
			72653,
			87288,
			14840,
			78293,
			12662,
			18531,
			31703,
			63951,
			29440,
			72462,
			70919,
			80101,
			44419,
			49638,
			69717,
			43226,
			63155,
			39824,
			45744,
			82720,
			80004,
			12678,
			49647,
			84066,
			71405,
			41383,
			36836,
			22137,
			88428,
			81555,
			43263,
			26312,
			9466,
			41962,
			16289,
			64462,
			72547,
			12694,
			77452,
			59794,
			22345,
			69938,
			35904,
			89116,
			38156,
			87908,
			4635,
			82416,
			18186,
			14705,
			72261,
			73747,
			12139,
			26937,
			42797,
			79941,
			43026,
			41765,
			87243,
			78688,
			40357,
			37505,
			71260,
			70463,
			25941,
			53660,
			87292,
			71227,
			53435,
			12147,
			9988,
			41973,
			40916,
			12226,
			45810,
			43156,
			80821,
			41751,
			42819,
			38849,
			71201,
			71135,
			78628,
			63118,
			70516,
			67906,
			41686,
			70797,
			68483,
			44939,
			70859,
			78809,
			20419,
			87256,
			27123,
			88995,
			9917,
			87264,
			72798,
			22297,
			49659,
			14727,
			77854,
			72012,
			88431,
			26522,
			73682,
			87916,
			71242,
			48324,
			22303,
			12163,
			9621,
			36865,
			72682,
			78687,
			71651,
			86965,
			10048,
			88984,
			72870,
			68227,
			8789,
			53046,
			64457,
			72406,
			14504,
			71391,
			89094,
			79224,
			70618,
			87265,
			72872,
			71013,
			72009,
			35587,
			26146,
			8563,
			71313,
			35599,
			63390,
			63080,
			52783,
			12721,
			71451,
			53047,
			35556,
			15402
		],
		"amount": [
			1,
			1,
			1,
			1,
			1,
			1,
			1,
			1,
			1,
			1,
			1,
			1,
			1,
			1,
			1,
			1,
			1,
			1,
			1,
			1,
			1,
			1,
			1,
			1,
			1,
			1,
			1,
			1,
			1,
			1,
			1,
			1,
			1,
			1,
			1,
			1,
			1,
			1,
			1,
			1,
			1,
			1,
			1,
			1,
			1,
			1,
			1,
			1,
			1,
			1,
			1,
			1,
			1,
			1,
			1,
			1,
			1,
			1,
			1,
			1,
			1,
			1,
			1,
			1,
			1,
			1,
			1,
			1,
			1,
			1,
			1,
			1,
			1,
			1,
			1,
			1,
			1,
			1,
			1,
			1,
			1,
			1,
			1,
			1,
			1,
			1,
			1,
			1,
			1,
			1,
			1,
			1,
			1,
			1,
			1,
			1,
			1,
			1,
			1,
			1,
			1,
			1,
			1,
			1,
			1,
			1,
			1,
			1,
			1,
			1,
			1,
			1,
			1,
			1,
			1,
			1,
			1,
			1,
			1,
			1,
			1,
			1,
			1,
			1,
			1,
			1,
			1,
			1,
			1,
			1,
			1,
			1,
			1,
			1,
			1,
			1,
			1,
			1,
			1,
			1,
			1,
			1,
			1,
			1,
			1,
			1,
			1,
			1,
			1,
			1,
			1,
			1,
			1,
			1,
			1,
			1,
			1,
			1,
			1,
			1,
			1,
			1,
			1,
			1,
			1,
			1,
			1,
			1,
			1,
			1,
			1
		],
		"quote_id": [
			null,
			null,
			null,
			null,
			null,
			null,
			null,
			null,
			null,
			null,
			null,
			null,
			null,
			null,
			null,
			null,
			null,
			null,
			null,
			null,
			null,
			null,
			null,
			null,
			null,
			null,
			null,
			null,
			null,
			null,
			null,
			null,
			null,
			null,
			null,
			null,
			null,
			null,
			null,
			null,
			null,
			null,
			null,
			null,
			null,
			null,
			null,
			null,
			null,
			null,
			null,
			null,
			null,
			null,
			null,
			null,
			null,
			null,
			null,
			null,
			null,
			null,
			null,
			null,
			null,
			null,
			null,
			null,
			null,
			null,
			null,
			null,
			null,
			null,
			null,
			null,
			null,
			null,
			null,
			null,
			null,
			null,
			null,
			null,
			null,
			null,
			null,
			null,
			null,
			null,
			null,
			null,
			null,
			null,
			null,
			null,
			null,
			null,
			null,
			null,
			null,
			null,
			null,
			null,
			null,
			null,
			null,
			null,
			null,
			null,
			null,
			null,
			null,
			null,
			null,
			null,
			null,
			null,
			null,
			null,
			null,
			null,
			null,
			null,
			null,
			null,
			null,
			null,
			null,
			null,
			null,
			null,
			null,
			null,
			null,
			null,
			null,
			null,
			null,
			null,
			null,
			null,
			null,
			null,
			null,
			null,
			null,
			null,
			null,
			null,
			null,
			null,
			null,
			null,
			null,
			null,
			null,
			null,
			null,
			null,
			null,
			null,
			null,
			null,
			null,
			null,
			null,
			null,
			null,
			null,
			null
		],
		"supplier": [
			null,
			null,
			null,
			null,
			null,
			null,
			null,
			null,
			null,
			null,
			null,
			null,
			null,
			null,
			null,
			null,
			null,
			null,
			null,
			null,
			null,
			null,
			null,
			null,
			null,
			null,
			null,
			null,
			null,
			null,
			null,
			null,
			null,
			null,
			null,
			null,
			null,
			null,
			null,
			null,
			null,
			null,
			null,
			null,
			null,
			null,
			null,
			null,
			null,
			null,
			null,
			null,
			null,
			null,
			null,
			null,
			null,
			null,
			null,
			null,
			null,
			null,
			null,
			null,
			null,
			null,
			null,
			null,
			null,
			null,
			null,
			null,
			null,
			null,
			null,
			null,
			null,
			null,
			null,
			null,
			null,
			null,
			null,
			null,
			null,
			null,
			null,
			null,
			null,
			null,
			null,
			null,
			null,
			null,
			null,
			null,
			null,
			null,
			null,
			null,
			null,
			null,
			null,
			null,
			null,
			null,
			null,
			null,
			null,
			null,
			null,
			null,
			null,
			null,
			null,
			null,
			null,
			null,
			null,
			null,
			null,
			null,
			null,
			null,
			null,
			null,
			null,
			null,
			null,
			null,
			null,
			null,
			null,
			null,
			null,
			null,
			null,
			null,
			null,
			null,
			null,
			null,
			null,
			null,
			null,
			null,
			null,
			null,
			null,
			null,
			null,
			null,
			null,
			null,
			null,
			null,
			null,
			null,
			null,
			null,
			null,
			null,
			null,
			null,
			null,
			null,
			null,
			null,
			null,
			null,
			null
		],
		"max_lead_time": [
			null,
			null,
			null,
			null,
			null,
			null,
			null,
			null,
			null,
			null,
			null,
			null,
			null,
			null,
			null,
			null,
			null,
			null,
			null,
			null,
			null,
			null,
			null,
			null,
			null,
			null,
			null,
			null,
			null,
			null,
			null,
			null,
			null,
			null,
			null,
			null,
			null,
			null,
			null,
			null,
			null,
			null,
			null,
			null,
			null,
			null,
			null,
			null,
			null,
			null,
			null,
			null,
			null,
			null,
			null,
			null,
			null,
			null,
			null,
			null,
			null,
			null,
			null,
			null,
			null,
			null,
			null,
			null,
			null,
			null,
			null,
			null,
			null,
			null,
			null,
			null,
			null,
			null,
			null,
			null,
			null,
			null,
			null,
			null,
			null,
			null,
			null,
			null,
			null,
			null,
			null,
			null,
			null,
			null,
			null,
			null,
			null,
			null,
			null,
			null,
			null,
			null,
			null,
			null,
			null,
			null,
			null,
			null,
			null,
			null,
			null,
			null,
			null,
			null,
			null,
			null,
			null,
			null,
			null,
			null,
			null,
			null,
			null,
			null,
			null,
			null,
			null,
			null,
			null,
			null,
			null,
			null,
			null,
			null,
			null,
			null,
			null,
			null,
			null,
			null,
			null,
			null,
			null,
			null,
			null,
			null,
			null,
			null,
			null,
			null,
			null,
			null,
			null,
			null,
			null,
			null,
			null,
			null,
			null,
			null,
			null,
			null,
			null,
			null,
			null,
			null,
			null,
			null,
			null,
			null,
			null
		],
		"quoted_amount": [
			null,
			null,
			null,
			null,
			null,
			null,
			null,
			null,
			null,
			null,
			null,
			null,
			null,
			null,
			null,
			null,
			null,
			null,
			null,
			null,
			null,
			null,
			null,
			null,
			null,
			null,
			null,
			null,
			null,
			null,
			null,
			null,
			null,
			null,
			null,
			null,
			null,
			null,
			null,
			null,
			null,
			null,
			null,
			null,
			null,
			null,
			null,
			null,
			null,
			null,
			null,
			null,
			null,
			null,
			null,
			null,
			null,
			null,
			null,
			null,
			null,
			null,
			null,
			null,
			null,
			null,
			null,
			null,
			null,
			null,
			null,
			null,
			null,
			null,
			null,
			null,
			null,
			null,
			null,
			null,
			null,
			null,
			null,
			null,
			null,
			null,
			null,
			null,
			null,
			null,
			null,
			null,
			null,
			null,
			null,
			null,
			null,
			null,
			null,
			null,
			null,
			null,
			null,
			null,
			null,
			null,
			null,
			null,
			null,
			null,
			null,
			null,
			null,
			null,
			null,
			null,
			null,
			null,
			null,
			null,
			null,
			null,
			null,
			null,
			null,
			null,
			null,
			null,
			null,
			null,
			null,
			null,
			null,
			null,
			null,
			null,
			null,
			null,
			null,
			null,
			null,
			null,
			null,
			null,
			null,
			null,
			null,
			null,
			null,
			null,
			null,
			null,
			null,
			null,
			null,
			null,
			null,
			null,
			null,
			null,
			null,
			null,
			null,
			null,
			null,
			null,
			null,
			null,
			null,
			null,
			null
		]
	},
	"reaction_ids": [
		26625,
		58882,
		14,
		57872,
		17,
		18,
		65042,
		65041,
		14363,
		29,
		33,
		35,
		37,
		56359,
		43,
		27692,
		18477,
		54315,
		31284,
		56884,
		54,
		4154,
		61,
		58429,
		38463,
		31295,
		58432,
		33858,
		38471,
		34381,
		82,
		38482,
		85,
		73814,
		58967,
		41048,
		57434,
		25694,
		94,
		65632,
		73827,
		28262,
		103,
		105,
		56937,
		73835,
		108,
		73836,
		3695,
		27249,
		34422,
		69241,
		54905,
		32382,
		10370,
		73859,
		73863,
		54421,
		21141,
		64665,
		50332,
		19102,
		159,
		65192,
		50349,
		14520,
		18106,
		67258,
		14526,
		59073,
		50378,
		57039,
		6354,
		57556,
		58072,
		59102,
		6370,
		64227,
		14566,
		60134,
		7402,
		57340,
		6386,
		74485,
		7927,
		74493,
		18687,
		32512,
		6411,
		41741,
		57622,
		73499,
		68897,
		5921,
		31011,
		60199,
		5929,
		4398,
		57648,
		25392,
		75570,
		58681,
		5945,
		75581,
		57663,
		32582,
		25417,
		56138,
		8525,
		59215,
		63825,
		57681,
		7508,
		25428,
		19288,
		37209,
		51546,
		66396,
		51551,
		51040,
		47972,
		31076,
		7526,
		32619,
		12652,
		31090,
		4469,
		75639,
		6008,
		54650,
		75646,
		41343,
		41344,
		57218,
		57734,
		18311,
		50568,
		32138,
		63375,
		63376,
		63379,
		63381,
		63382,
		59286,
		59288,
		35225,
		66461,
		7584,
		32160,
		37283,
		29604,
		37286,
		68007,
		22960,
		4529,
		29115,
		70587,
		57280,
		37320,
		58826,
		75731,
		64980,
		57812,
		35291,
		30684,
		30172,
		4062,
		41952,
		57826,
		26597,
		75753,
		3565,
		66547,
		10745,
		25596
	],
	"rgen_data_path": "/opt/xchem-fragalysis-2/maxwin/CHIKV_HIPPO/hippo_prod/CHIKV_prod8b_rgen.json",
	"rgen_db_path": "/opt/xchem-fragalysis-2/maxwin/CHIKV_HIPPO/hippo_prod/CHIKV_prod8b.sqlite",
	"rgen_recipe_dir": "/opt/xchem-fragalysis-2/maxwin/CHIKV_HIPPO/hippo_prod/CHIKV_prod8b_recipes",
	"rgen_max_lead_time": null,
	"rgen_suppliers": [
		"Stock",
		"Enamine"
	],
	"gen_budget": 11000,
	"gen_currency": "EUR",
	"gen_max_products": 1200,
	"gen_max_reactions": 3000,
	"gen_max_iter": 5000,
	"gen_shuffle": true,
	"gen_iterations": 4999,
	"gen_stop_reason": "Max #iterations reached",
	"gen_recipe_path": "/opt/xchem-fragalysis-2/maxwin/CHIKV_HIPPO/hippo_prod/CHIKV_prod8b_recipes/Recipe_1GEDP9Z.json"
}